fasthug/__init__.py
fasthug/__main__.py
fasthug/bench.py
fasthug/fasthug.py
fasthug-0.0.6.dist-info/licenses/LICENSE
tests/test_basic.py
tests/test_bench.py
tests/test_generate.py
tests/test_quantization.py
utils/app.py
utils/plot.py
fasthug-0.0.6.dist-info/METADATA
fasthug-0.0.6.dist-info/WHEEL
fasthug-0.0.6.dist-info/entry_points.txt
fasthug-0.0.6.dist-info/top_level.txt
fasthug-0.0.6.dist-info/RECORD
