Metadata-Version: 2.4
Name: fasthug
Version: 0.0.6
Summary: Load HuggingFace Large Language Models 5x faster
Author: Alvin Wan
License: MIT License
Requires-Python: >=3.9
License-File: LICENSE
Requires-Dist: torch
Requires-Dist: transformers
Requires-Dist: accelerate
Requires-Dist: numpy
Requires-Dist: huggingface_hub
Requires-Dist: tabulate
Dynamic: license-file
